fullcontrol/README.md
fullcontrol/__init__.py
fullcontrol/auxilliary_components.py
fullcontrol/base.py
fullcontrol/check.py
fullcontrol/common.py
fullcontrol/extra_functions.py
fullcontrol/extrusion_classes.py
fullcontrol/point.py
fullcontrol/printer.py
fullcontrol/combinations/__init__.py
fullcontrol/combinations/gcode_and_visualize/__init__.py
fullcontrol/combinations/gcode_and_visualize/classes.py
fullcontrol/combinations/gcode_and_visualize/common.py
fullcontrol/devices/community/__init__.py
fullcontrol/devices/community/readme.md
fullcontrol/devices/community/singletool/__init__.py
fullcontrol/devices/community/singletool/bambulab_x1.py
fullcontrol/devices/community/singletool/base_settings.py
fullcontrol/devices/community/singletool/cr_10.py
fullcontrol/devices/community/singletool/custom.py
fullcontrol/devices/community/singletool/ender_3.py
fullcontrol/devices/community/singletool/ender_5_plus.py
fullcontrol/devices/community/singletool/generic.py
fullcontrol/devices/community/singletool/prusa_i3.py
fullcontrol/devices/community/singletool/prusa_mini.py
fullcontrol/devices/community/singletool/prusa_mk4.py
fullcontrol/devices/community/singletool/raise3d_pro2_nozzle1.py
fullcontrol/devices/community/singletool/toolchanger_T0.py
fullcontrol/devices/community/singletool/toolchanger_T1.py
fullcontrol/devices/community/singletool/toolchanger_T2.py
fullcontrol/devices/community/singletool/toolchanger_T3.py
fullcontrol/devices/community/singletool/ultimaker2plus.py
fullcontrol/devices/community/singletool/voron_zero.py
fullcontrol/devices/community/singletool/wasp2040clay.py
fullcontrol/devices/community_minimal/__init__.py
fullcontrol/devices/community_minimal/library.json
fullcontrol/devices/community_minimal/template.py
fullcontrol/devices/community_minimal/settings/__init__.py
fullcontrol/devices/community_minimal/settings/generic.py
fullcontrol/devices/cura/__init__.py
fullcontrol/devices/cura/library.json
fullcontrol/devices/cura/settings/101Hero.py
fullcontrol-0.1.2.dist-info/METADATA
fullcontrol-0.1.2.dist-info/WHEEL
fullcontrol-0.1.2.dist-info/RECORD
