Metadata-Version: 2.4
Name: fullcontrol
Version: 0.1.2
Summary: fullcontrol - unconstrained design
Project-URL: Homepage, https://fullcontrol.xyz
Project-URL: Repository, https://github.com/FullControlXYZ/fullcontrol
Project-URL: Documentation, https://github.com/FullControlXYZ/fullcontrol/tree/master/docs
Project-URL: Tutorials, https://github.com/FullControlXYZ/fullcontrol/tree/master/tutorials
Project-URL: Bug Tracker, https://github.com/FullControlXYZ/fullcontrol/issues
Author-email: Andy Gleadall <andy@fullcontrol.xyz>, Dirk Leas <dirk@fullcontrol.xyz>
Classifier: License :: OSI Approved :: GNU General Public License v3 (GPLv3)
Classifier: Operating System :: OS Independent
Classifier: Programming Language :: Python :: 3
Requires-Python: >=3.10
Requires-Dist: numpy
Requires-Dist: plotly
Requires-Dist: pydantic
